imgifconvt/__init__.py
imgifconvt/converter.py
imgifconvt-1.0.1.dist-info/LICENSE
imgifconvt-1.0.1.dist-info/METADATA
imgifconvt-1.0.1.dist-info/WHEEL
imgifconvt-1.0.1.dist-info/top_level.txt
imgifconvt-1.0.1.dist-info/RECORD
